pySingleFile/__init__.py
pySingleFile/singlefile.py
pySingleFile/DrissionPage/__init__.py
pySingleFile/DrissionPage/common.py
pySingleFile/DrissionPage/errors.py
pySingleFile/DrissionPage/items.py
pySingleFile/DrissionPage/_base/base.py
pySingleFile/DrissionPage/_base/base.pyi
pySingleFile/DrissionPage/_base/browser.py
pySingleFile/DrissionPage/_base/browser.pyi
pySingleFile/DrissionPage/_base/driver.py
pySingleFile/DrissionPage/_base/driver.pyi
pySingleFile/DrissionPage/_configs/chromium_options.py
pySingleFile/DrissionPage/_configs/chromium_options.pyi
pySingleFile/DrissionPage/_configs/configs.ini
pySingleFile/DrissionPage/_configs/options_manage.py
pySingleFile/DrissionPage/_configs/options_manage.pyi
pySingleFile/DrissionPage/_configs/session_options.py
pySingleFile/DrissionPage/_configs/session_options.pyi
pySingleFile/DrissionPage/_elements/chromium_element.py
pySingleFile/DrissionPage/_elements/chromium_element.pyi
pySingleFile/DrissionPage/_elements/none_element.py
pySingleFile/DrissionPage/_elements/session_element.py
pySingleFile/DrissionPage/_elements/session_element.pyi
pySingleFile/DrissionPage/_functions/browser.py
pySingleFile/DrissionPage/_functions/browser.pyi
pySingleFile/DrissionPage/_functions/by.py
pySingleFile/DrissionPage/_functions/cli.py
pySingleFile/DrissionPage/_functions/keys.py
pySingleFile/DrissionPage/_functions/keys.pyi
pySingleFile/DrissionPage/_functions/locator.py
pySingleFile/DrissionPage/_functions/locator.pyi
pySingleFile/DrissionPage/_functions/settings.py
pySingleFile/DrissionPage/_functions/tools.py
pySingleFile/DrissionPage/_functions/tools.pyi
pySingleFile/DrissionPage/_functions/web.py
pySingleFile/DrissionPage/_functions/web.pyi
pySingleFile/DrissionPage/_pages/chromium_base.py
pySingleFile/DrissionPage/_pages/chromium_base.pyi
pySingleFile/DrissionPage/_pages/chromium_frame.py
pySingleFile/DrissionPage/_pages/chromium_frame.pyi
pySingleFile/DrissionPage/_pages/chromium_page.py
pySingleFile-0.1.4.dist-info/METADATA
pySingleFile-0.1.4.dist-info/WHEEL
pySingleFile-0.1.4.dist-info/top_level.txt
pySingleFile-0.1.4.dist-info/RECORD
