Metadata-Version: 2.1
Name: pySingleFile
Version: 0.1.4
Summary: Python Implementation of SingleFile
Home-page: https://github.com/MrWQ/pySingleFile
Author: ordar
Author-email: w666q@qq.com
License: BSD
Keywords: SingleFile
Platform: UNKNOWN
Classifier: Programming Language :: Python :: 3.6
Classifier: Development Status :: 3 - Alpha
Classifier: Topic :: Utilities
Classifier: License :: OSI Approved :: BSD License
Requires-Python: >=3.6
Requires-Dist: lxml
Requires-Dist: requests
Requires-Dist: cssselect
Requires-Dist: DownloadKit (>=2.0.0)
Requires-Dist: websocket-client
Requires-Dist: click
Requires-Dist: tldextract
Requires-Dist: psutil
